dataexec/'
dataexec/__about__.py
dataexec/__init__.py
dataexec/assets.py
dataexec/base.py
dataexec/tasks.py
dataexec/types.py
dataexec/utils.py
dataexec-0.0.1.dist-info/METADATA
dataexec-0.0.1.dist-info/WHEEL
dataexec-0.0.1.dist-info/licenses/LICENSE.txt
dataexec-0.0.1.dist-info/RECORD
